setup.cfg
setup.py
rakam_client/__init__.py
rakam_client/api_client.py
rakam_client/configuration.py
rakam_client/rest.py
rakam_client.egg-info/PKG-INFO
rakam_client.egg-info/SOURCES.txt
rakam_client.egg-info/dependency_links.txt
rakam_client.egg-info/requires.txt
rakam_client.egg-info/top_level.txt
rakam_client/apis/__init__.py
rakam_client/apis/admin_api.py
rakam_client/apis/collect_api.py
rakam_client/apis/continuousquery_api.py
rakam_client/apis/eventexplorer_api.py
rakam_client/apis/funnel_api.py
rakam_client/apis/materializedview_api.py
rakam_client/apis/query_api.py
rakam_client/apis/realtime_api.py
rakam_client/apis/recipe_api.py
rakam_client/apis/retention_api.py
rakam_client/apis/user_api.py
rakam_client/apis/useraction_api.py
rakam_client/models/__init__.py
rakam_client/models/analyze_request.py
rakam_client/models/bulk_event_remote.py
rakam_client/models/check_lock_key.py
rakam_client/models/collection.py
rakam_client/models/collection_definition.py
rakam_client/models/collection_event.py
rakam_client/models/commit_bulk_events.py
rakam_client/models/commit_request.py
rakam_client/models/condition.py
rakam_client/models/config_item.py
rakam_client/models/continuous_query.py
rakam_client/models/continuous_query_delete_query.py
rakam_client/models/continuous_query_get_query.py
rakam_client/models/continuous_query_get_schema_of_query.py
rakam_client/models/continuous_query_test_query.py
rakam_client/models/create_precomputed_table.py
rakam_client/models/create_project.py
rakam_client/models/email_action_config.py
rakam_client/models/error_message.py
rakam_client/models/event.py
rakam_client/models/event_context.py
rakam_client/models/event_explorer_get_event_statistics.py
rakam_client/models/event_filter.py
rakam_client/models/event_filter_aggregation.py
rakam_client/models/event_list.py
rakam_client/models/execute.py
rakam_client/models/explain.py
rakam_client/models/export_query.py
rakam_client/models/funnel_query.py
rakam_client/models/funnel_step.py
rakam_client/models/funnel_window.py
rakam_client/models/group_by.py
rakam_client/models/library.py
rakam_client/models/mapping_plugin.py
rakam_client/models/materialized_view.py
